heif_convert/__init__.py
heif_convert/__main__.py
heif_convert/_version.py
heif_convert-1.2.1.dist-info/LICENSE
heif_convert-1.2.1.dist-info/METADATA
heif_convert-1.2.1.dist-info/WHEEL
heif_convert-1.2.1.dist-info/entry_points.txt
heif_convert-1.2.1.dist-info/top_level.txt
heif_convert-1.2.1.dist-info/RECORD
