Metadata-Version: 2.1
Name: heif-convert
Version: 1.2.1
Summary: Multi-Platform command line tool written in Python to convert HEIF images
Home-page: https://github.com/NeverMendel/heif-convert
Author: Davide Cazzin
Author-email: 28535750+NeverMendel@users.noreply.github.com
License: MIT
Keywords: heif,heic,heif-convert,heic-convert
Classifier: Programming Language :: Python :: 3
Classifier: Programming Language :: Python :: 3.8
Classifier: License :: OSI Approved :: MIT License
Classifier: Operating System :: OS Independent
Requires-Python: >=3.7
License-File: LICENSE
Requires-Dist: Pillow
Requires-Dist: pillow-heif
